myapp/__init__.py
myapp/app.py
myapp/static/script.js
myapp/static/styles.css
myapp/templates/index.html
myapp_betrand1999-5.0.1.dist-info/METADATA
myapp_betrand1999-5.0.1.dist-info/WHEEL
myapp_betrand1999-5.0.1.dist-info/entry_points.txt
myapp_betrand1999-5.0.1.dist-info/top_level.txt
myapp_betrand1999-5.0.1.dist-info/RECORD
