Metadata-Version: 2.4
Name: myapp-betrand1999
Version: 5.0.1
Requires-Dist: flask
Dynamic: requires-dist
